arc_verifier/__init__.py
arc_verifier/__version__.py
arc_verifier/api.py
arc_verifier/models.py
arc_verifier/analysis/__init__.py
arc_verifier/analysis/performance.py
arc_verifier/analysis/strategy.py
arc_verifier/analysis/llm_judge/__init__.py
arc_verifier/analysis/llm_judge/core.py
arc_verifier/analysis/llm_judge/models.py
arc_verifier/analysis/llm_judge/utils.py
arc_verifier/analysis/llm_judge/evaluation/__init__.py
arc_verifier/analysis/llm_judge/evaluation/ensemble.py
arc_verifier/analysis/llm_judge/evaluation/prompts.py
arc_verifier/analysis/llm_judge/providers/__init__.py
arc_verifier/analysis/llm_judge/providers/anthropic.py
arc_verifier/analysis/llm_judge/providers/base.py
arc_verifier/analysis/llm_judge/providers/factory.py
arc_verifier/analysis/llm_judge/providers/openai.py
arc_verifier/analysis/llm_judge/security/__init__.py
arc_verifier/analysis/llm_judge/security/analyzers.py
arc_verifier/analysis/llm_judge/security/prompts.py
arc_verifier/analysis/llm_judge/security/scoring.py
arc_verifier/cli/__init__.py
arc_verifier/cli/__main__.py
arc_verifier/cli/commands/__init__.py
arc_verifier/cli/commands/components.py
arc_verifier/cli/commands/config.py
arc_verifier/cli/commands/data.py
arc_verifier/cli/commands/export.py
arc_verifier/cli/commands/management.py
arc_verifier/cli/commands/verification.py
arc_verifier/cli/display/__init__.py
arc_verifier/cli/display/performance.py
arc_verifier/cli/display/simulation.py
arc_verifier/cli/display/terminal.py
arc_verifier/cli/initialization/__init__.py
arc_verifier/cli/initialization/config.py
arc_verifier/cli/initialization/detection.py
arc_verifier/cli/initialization/setup.py
arc_verifier/cli/scoring/__init__.py
arc_verifier/cli/scoring/fort_score.py
arc_verifier/cli/scoring/status.py
arc_verifier/core/__init__.py
arc_verifier/core/pipeline.py
arc_verifier/core/verifier.py
arc_verifier/data/__init__.py
arc_verifier/data/backtester.py
arc_verifier/data/fetcher.py
arc_verifier/data/registry.py
arc_verifier-0.1.2.dist-info/licenses/LICENSE
arc_verifier-0.1.2.dist-info/METADATA
arc_verifier-0.1.2.dist-info/WHEEL
arc_verifier-0.1.2.dist-info/entry_points.txt
arc_verifier-0.1.2.dist-info/top_level.txt
arc_verifier-0.1.2.dist-info/RECORD
