Metadata-Version: 2.4
Name: arc-verifier
Version: 0.1.2
Summary: Verification and evaluation framework for autonomous agents across agentic protocols
Home-page: https://github.com/arc-computer/arc-verifier
Author: Arc-Verifier Contributors
Author-email: 
License: MIT
Project-URL: Homepage, https://github.com/arc-computer/arc-verifier
Project-URL: Documentation, https://github.com/arc-computer/arc-verifier/tree/main/docs
Project-URL: Repository, https://github.com/arc-computer/arc-verifier
Project-URL: Issues, https://github.com/arc-computer/arc-verifier/issues
Keywords: near,agents,verification,tee,docker,security
Classifier: Development Status :: 4 - Beta
Classifier: Intended Audience :: Developers
Classifier: Topic :: Software Development :: Testing
Classifier: Topic :: Security
Classifier: Topic :: Scientific/Engineering :: Artificial Intelligence
Classifier: License :: OSI Approved :: MIT License
Classifier: Programming Language :: Python :: 3
Classifier: Programming Language :: Python :: 3.11
Classifier: Programming Language :: Python :: 3.12
Classifier: Operating System :: OS Independent
Requires-Python: >=3.11
License-File: LICENSE
Requires-Dist: click>=8.1.0
Requires-Dist: docker>=6.0.0
Requires-Dist: rich>=13.0.0
Requires-Dist: pyyaml>=6.0.0
Requires-Dist: pydantic>=2.0.0
Requires-Dist: httpx>=0.24.0
Requires-Dist: python-dotenv>=1.0.0
Requires-Dist: aiohttp>=3.9.0
Requires-Dist: dagger-io>=0.6.0
Requires-Dist: cryptography>=41.0.0
Requires-Dist: pandas>=2.0.0
Requires-Dist: numpy>=1.24.0
Requires-Dist: requests>=2.31.0
Requires-Dist: aiofiles>=23.0.0
Requires-Dist: python-dateutil>=2.8.0
Provides-Extra: dev
Requires-Dist: pytest>=7.4.0; extra == "dev"
Requires-Dist: pytest-asyncio>=0.21.0; extra == "dev"
Requires-Dist: pytest-timeout>=2.1.0; extra == "dev"
Requires-Dist: black>=23.7.0; extra == "dev"
Requires-Dist: mypy>=1.4.0; extra == "dev"
Requires-Dist: ruff>=0.1.0; extra == "dev"
Requires-Dist: coverage>=7.0.0; extra == "dev"
Dynamic: home-page
Dynamic: license-file
Dynamic: requires-python
